yr_cli/__init__.py
yr_cli/api.py
yr_cli/cache.py
yr_cli/cli.py
yr_cli/commands.py
yr_cli/interface.py
yr_cli/maps.py
yr_cli/utils.py
yr_cli/icons/__init__.py
yr_cli/icons/clearsky_day.png
yr_cli/icons/clearsky_night.png
yr_cli/icons/clearsky_polartwilight.png
yr_cli/icons/cloudy.png
yr_cli/icons/fair_day.png
yr_cli/icons/fair_night.png
yr_cli/icons/fair_polartwilight.png
yr_cli/icons/fog.png
yr_cli/icons/heavyrain.png
yr_cli/icons/heavyrainandthunder.png
yr_cli/icons/heavyrainshowers_day.png
yr_cli/icons/heavyrainshowers_night.png
yr_cli/icons/heavyrainshowers_polartwilight.png
yr_cli/icons/heavyrainshowersandthunder_day.png
yr_cli/icons/heavyrainshowersandthunder_night.png
yr_cli/icons/heavyrainshowersandthunder_polartwilight.png
yr_cli/icons/heavysleet.png
yr_cli/icons/heavysleetandthunder.png
yr_cli/icons/heavysleetshowers_day.png
yr_cli/icons/heavysleetshowers_night.png
yr_cli/icons/heavysleetshowers_polartwilight.png
yr_cli/icons/heavysleetshowersandthunder_day.png
yr_cli/icons/heavysleetshowersandthunder_night.png
yr_cli/icons/heavysleetshowersandthunder_polartwilight.png
yr_cli/icons/heavysnow.png
yr_cli/icons/heavysnowandthunder.png
yr_cli/icons/heavysnowshowers_day.png
yr_cli/icons/heavysnowshowers_night.png
yr_cli/icons/heavysnowshowers_polartwilight.png
yr_cli/icons/heavysnowshowersandthunder_day.png
yr_cli/icons/heavysnowshowersandthunder_night.png
yr_cli/icons/heavysnowshowersandthunder_polartwilight.png
yr_cli/icons/lightrain.png
yr_cli/icons/lightrainandthunder.png
yr_cli/icons/lightrainshowers_day.png
yr_cli/icons/lightrainshowers_night.png
yr_cli/icons/lightrainshowers_polartwilight.png
yr_cli/icons/lightrainshowersandthunder_day.png
yr_cli/icons/lightrainshowersandthunder_night.png
yr_cli/icons/lightrainshowersandthunder_polartwilight.png
yr_cli/icons/lightsleet.png
yr_cli/icons/lightsleetandthunder.png
yr_cli/icons/lightsleetshowers_day.png
yr_cli/icons/lightsleetshowers_night.png
yr_cli/icons/lightsleetshowers_polartwilight.png
yr_cli-0.0.4.dist-info/METADATA
yr_cli-0.0.4.dist-info/WHEEL
yr_cli-0.0.4.dist-info/entry_points.txt
yr_cli-0.0.4.dist-info/top_level.txt
yr_cli-0.0.4.dist-info/RECORD
