Metadata-Version: 2.1
Name: yr-cli
Version: 0.0.4
Summary: A rich CLI for location-based weather forecasts
Author-email: Tim Wolff-Piggott <twolffpiggott@gmail.com>
Project-URL: Homepage, https://github.com/twolffpiggott/yr-cli
Keywords: yr,weather,cli,command line
Classifier: License :: OSI Approved :: GNU General Public License v3 (GPLv3)
Classifier: Operating System :: Microsoft :: Windows
Classifier: Operating System :: MacOS
Classifier: Operating System :: POSIX :: Linux
Classifier: Programming Language :: Python :: 3.12
Requires-Python: >=3.12
Requires-Dist: inquirer>=3.4.0
Requires-Dist: requests>=2.32.3
Requires-Dist: requests-cache==1.2.1
Requires-Dist: rich>=13.8.0
Requires-Dist: py-staticmaps==0.4.0
Requires-Dist: typer>=0.12.5
Requires-Dist: urllib3>=2.2.2
Provides-Extra: dev
Requires-Dist: pytest>=8.3.3; extra == "dev"
Requires-Dist: black>=24.8.0; extra == "dev"
Requires-Dist: flake8>=7.1.1; extra == "dev"
Requires-Dist: ipdb; extra == "dev"
Requires-Dist: isort>=5.13.2; extra == "dev"
Requires-Dist: pre-commit; extra == "dev"
Provides-Extra: test
Requires-Dist: pytest>=8.3.3; extra == "test"
